teledigest/__init__.py
teledigest/config.py
teledigest/db.py
teledigest/llm.py
teledigest/main.py
teledigest/scheduler.py
teledigest/telegram_client.py
teledigest-0.1.0.dist-info/METADATA
teledigest-0.1.0.dist-info/WHEEL
teledigest-0.1.0.dist-info/entry_points.txt
teledigest-0.1.0.dist-info/licenses/LICENSE
teledigest-0.1.0.dist-info/RECORD
