Metadata-Version: 2.4
Name: teledigest
Version: 0.1.0
Summary: LLM-driven Telegram digest bot
License-Expression: MIT
License-File: LICENSE
Author: Igor Opaniuk
Author-email: igor.opaniuk@gmail.com
Requires-Python: >=3.12
Classifier: Programming Language :: Python :: 3
Classifier: Programming Language :: Python :: 3.12
Classifier: Programming Language :: Python :: 3.13
Classifier: Programming Language :: Python :: 3.14
Requires-Dist: openai (>=2.9.0,<3.0.0)
Requires-Dist: platformdirs (>=4.5.1,<5.0.0)
Requires-Dist: python-dotenv (>=1.2.1,<2.0.0)
Requires-Dist: sqlite-utils (>=3.39,<4.0)
Requires-Dist: telethon (>=1.42.0,<2.0.0)
